kydb/__init__.py
kydb/api.py
kydb/base.py
kydb/cache.py
kydb/cache_context.py
kydb/config.py
kydb/dbobj.py
kydb/exceptions.py
kydb/folder_meta.py
kydb/interface.py
kydb/objdb.py
kydb/union.py
kydb/impl/dynamodb.py
kydb/impl/files.py
kydb/impl/http.py
kydb/impl/https.py
kydb/impl/memory.py
kydb/impl/redis.py
kydb/impl/s3.py
kydb-0.7.5.dist-info/LICENSE
kydb-0.7.5.dist-info/METADATA
kydb-0.7.5.dist-info/WHEEL
kydb-0.7.5.dist-info/top_level.txt
kydb-0.7.5.dist-info/RECORD
