Metadata-Version: 2.1
Name: kydb
Version: 0.7.5
Summary: kydb (Kinyu Database). NoSQL DB interface.
Home-page: https://github.com/tayglobal/kydb
Author: Tony Yum
Author-email: tony.yum@tayglobal.com
License: MIT
Keywords: NoSQL,Database,DB
Classifier: Development Status :: 3 - Alpha
Classifier: Intended Audience :: Developers
Classifier: Topic :: Software Development :: Build Tools
Classifier: License :: OSI Approved :: MIT License
Requires-Python: >=3.10
License-File: LICENSE
Requires-Dist: boto3
Requires-Dist: redis
Requires-Dist: pyyaml
